Verilog_Rev/cd.v
//Instead of compiling it creates a database storing the values
//Keywords : module , endmodule , input ,output
module e1(A,B,C,D);
	input A,B,C;
	output D;
	wire w1,w2;
	and a1(w1,A,B);
	not a2(w2,C);
	or a3(D,w1,w2);
endmodule

// Here sequential methods doesnt have any usage You are just defining what to do  

module e2(A,B,C,D);
	input A,B,C;
	output D;
	wire w1,w2;
	e3 i1(w1,A,B);
	e3 i2(D,w1,C);
	/*assign w1=(A&B);
	assign w2=~(C);
	assign D=(w1^w2);*/
endmodule

// Mistake : endmodule wont have semicolon
//eg2 is combinational logic
//primitive has output as the first element like not()
//not or and are all just primitives defined in the hdl library
//these modelling with primitives are called Gate-level modelling
// modelling with assign is called Data-flow modelling

primitive e3(C,A,B);
	input A,B;
	output C; 
	table
	0 0 : 0;
	0 1 : 1;
	1 0 : 1;
	1 1 : 0;
	endtable
endprimitive

module ha(S,C,a,b);
	input a,b;
	output S,C;
	assign S=(a^b);
	assign C=(a&b);
endmodule

module fa(S,C,a,b,c);
	input a,b,c;
	output S,C;
	wire w1;
	ha h1(w1,w2,a,b);
	ha h2(S,w3,w1,c);
	or o1(C,w3,w2);
endmodule	

module FA1(A,B,S,C);
	input [3:0] A,B;
	output [3:0] S;
	output C;
	wire c1,c2,c3;
	fa f1(S[0],c1,A[0],B[0],1'b0);
	fa f2(S[1],c2,A[1],B[1],c1);
	fa f3(S[2],c3,A[2],B[2],c2);
	fa f4(S[3],C,A[3],B[3],c3);
endmodule	
	
module FA2(A,B,S,C);
	input [3:0] A,B;
	output [3:0] S;
	output C;
	assign {C,S}=A+B;
endmodule
// The data-flow model has so many in-built symbols like {} is used to concatenate two variables 
/* 	+ is used to add two variables 
	- : subtract
	{> , < , ==} : greater than , less than , equal to
	? : is a comparator operator
*/
// assign a=(select>=8)?A:B;
	
//behavioural model must have output as reg
// It is used mostly in sequential circuits
//If statement can be used only in behavioural model

module b1(A,B,C);
	input A,B;
	output C;
	reg C;
	always@(A or B)
	if(A>B) assign C=A;
	else assign C=B;
endmodule

module ad1(A,B,C);
	input A,B;
	output reg[5:0] C;
	always@(A,B)
	if(A<B) C=6'b010101;
	else if(A>B) C=6'b011010;
	else C=6'b100011;
endmodule

//Lesson learnt never write a binary number in simple format ; write it with the prefix n'b

module ad2(A,B);
	input[15:0] A;
	output [15:0] B;
	assign B=A;
endmodule

//Single pass will never get over in single statement it will coninue forever eg : always initial
//We can modify it using two operators delay time operator # , event control operetor @	

//Event control operator takes care of the continuous assignment condition
//Blocking assignment will take place sequentially (a=b,b=a -> a=b=bi)
//Non-blocking assignment will take place concurrently (a<=b,b<=a -> a=bi,b=ai)


module D_F(D,clk,rst,Q);
	input D,clk,rst;
	output reg Q;
	always@(posedge clk,negedge rst)
	if(~(rst)) Q<=0;
	else Q<=D;
endmodule

module jk(J,K,clk,rst,Q);
	input J,K,clk,rst;
	output Q;
	wire w1,w2;
	assign w1=((J&~Q)|(~K&Q));
	D_F d(w1,clk,rst,Q);
endmodule

Verilog_Rev/tst.v
`timescale 1ns/100ps
// ` is used to include the compiler directory
/*module tst;
	// There is no input aand outputs here , It is just an interactive prog that gives commands
	// So inputs should be reg and outputs should be wires
	wire[15:0] S;
	//wire C;
	//reg[3:0] A,B;
	reg [15:0]A,B;
	//wire C,S;
	//e1 m1(A,B,C,D1);	
	//e2 m2(A,B,C,D2);
	//FA1 f1(A,B,S,C);
	//b1 e(A,B,C);
	ad2 a2(A,S);
	initial
	// statements under initial are executed once the stimulation starts to occur
		begin
			$dumpfile("tst_wave.vcd");
			$dumpvars(0,tst);
			A=16'b0;
			repeat(2<<16-1) #10 A+=1'b1;
			/*
			// BEGIN IS USED TO execute a set of statements under a block
			A=0000;B=0000;
			for(integer i=0;i<16;i++)
			begin
				for(integer j=0;j<15;j++)
				begin
					#10 B+=1;
				end
				#10 A+=1;B=0000;
			end
			A=0000;B=0000;
			repeat(15)
			begin
				repeat(15) #10 B+=1;
				#10 A+=1;
			end	
			#10;
					
		end
	//initial #2570 $finish;
	initial
		begin
			$display("A    S");
			$monitor("%b %d%d%d%d%d%d ryt?",A,S[15],S[14:12],S[11:9],S[8:6],S[5:3],S[2:0]);
		end
endmodule
*/
//Only one begin end statement for initial
//Each initial statement executes fromt he beginnng till the end
//monitor in the initial is executed only when the variables givem change


module tst2;
	reg J,K,clk,rst;
	wire Q;
	integer i=0;
	jk d1(J,K,clk,rst,Q);
	initial
		begin
			$dumpfile("tst_wave.vcd");
			$dumpvars(0,tst2);
			rst=0;clk=0;
			#10 rst=1;J=0;K=0;
			repeat(7) 
			begin
				#10 clk=~(clk);
				if((i%4)%2==1) K=1'b1;
				else if(i%4==2) 
				begin
					J=1'b1;
					K=1'b0;
				end
				else 
				begin
					J=1'b0;
					K=1'b0;
				end
				i+=1;
			end
			#10;
		end
	initial
		$monitor("J=%b K=%b Q=%b",J,K,Q);
endmodule
//Lesson learnt : even if it is a two variable assignment , do it in seperate lines

Verilog_Rev/tst_wave.vcd
$date
	Sun Apr 21 01:06:08 2024
$end
$version
	Icarus Verilog
$end
$timescale
	100ps
$end
$scope module tst2 $end
$var wire 1 ! Q $end
$var reg 1 " J $end
$var reg 1 # K $end
$var reg 1 $ clk $end
$var reg 1 % rst $end
$var integer 32 & i [31:0] $end
$scope module d1 $end
$var wire 1 " J $end
$var wire 1 # K $end
$var wire 1 $ clk $end
$var wire 1 % rst $end
$var wire 1 ' w1 $end
$var wire 1 ! Q $end
$scope module d $end
$var wire 1 ' D $end
$var wire 1 $ clk $end
$var wire 1 % rst $end
$var reg 1 ! Q $end
$upscope $end
$upscope $end
$upscope $end
$enddefinitions $end
#0
$dumpvars
x'
b0 &
0%
0$
x#
x"
0!
$end
#100
0'
0#
0"
1%
#200
b1 &
1$
#300
1'
b10 &
1"
0$
#400
1!
b11 &
1$
#500
b100 &
0"
0$
#600
b101 &
1$
#700
b110 &
1"
0$
#800
b111 &
1$
